{"numTotalTestSuites":4,"numPassedTestSuites":2,"numFailedTestSuites":2,"numPendingTestSuites":0,"numTotalTests":44,"numPassedTests":42,"numFailedTests":2,"numPendingTests":0,"numTodoTests":0,"snapshot":{"added":0,"failure":false,"filesAdded":0,"filesRemoved":0,"filesRemovedList":[],"filesUnmatched":0,"filesUpdated":0,"matched":0,"total":0,"unchecked":0,"uncheckedKeysByFile":[],"unmatched":0,"updated":0,"didUpdate":false},"startTime":1778164307051,"success":false,"testResults":[{"assertionResults":[{"ancestorTitles":["Exercício 01"],"fullName":"Exercício 01 Ex01 - Válida - Questão 1","status":"passed","title":"Ex01 - Válida - Questão 1","duration":1.972110000000015,"failureMessages":[],"meta":{}},{"ancestorTitles":["Exercício 01"],"fullName":"Exercício 01 Ex01 - Correta - Questão 1","status":"passed","title":"Ex01 - Correta - Questão 1","duration":1.0167819999999779,"failureMessages":[],"meta":{}},{"ancestorTitles":["Exercício 01"],"fullName":"Exercício 01 Ex01 - Válida - Questão 2","status":"passed","title":"Ex01 - Válida - Questão 2","duration":0.23335200000002487,"failureMessages":[],"meta":{}},{"ancestorTitles":["Exercício 01"],"fullName":"Exercício 01 Ex01 - Correta - Questão 2","status":"passed","title":"Ex01 - Correta - Questão 2","duration":0.3492230000000234,"failureMessages":[],"meta":{}},{"ancestorTitles":["Exercício 01"],"fullName":"Exercício 01 Ex01 - Válida - Questão 3","status":"passed","title":"Ex01 - Válida - Questão 3","duration":0.18956799999997997,"failureMessages":[],"meta":{}},{"ancestorTitles":["Exercício 01"],"fullName":"Exercício 01 Ex01 - Correta - Questão 3","status":"passed","title":"Ex01 - Correta - Questão 3","duration":0.11796300000000315,"failureMessages":[],"meta":{}},{"ancestorTitles":["Exercício 01"],"fullName":"Exercício 01 Ex01 - Válida - Questão 4","status":"passed","title":"Ex01 - Válida - Questão 4","duration":0.24789599999999723,"failureMessages":[],"meta":{}},{"ancestorTitles":["Exercício 01"],"fullName":"Exercício 01 Ex01 - Correta - Questão 4","status":"passed","title":"Ex01 - Correta - Questão 4","duration":0.1423639999999864,"failureMessages":[],"meta":{}},{"ancestorTitles":["Exercício 01"],"fullName":"Exercício 01 Ex01 - Válida - Questão 5","status":"passed","title":"Ex01 - Válida - Questão 5","duration":0.3746010000000126,"failureMessages":[],"meta":{}},{"ancestorTitles":["Exercício 01"],"fullName":"Exercício 01 Ex01 - Correta - Questão 5","status":"passed","title":"Ex01 - Correta - Questão 5","duration":0.3611049999999807,"failureMessages":[],"meta":{}},{"ancestorTitles":["Exercício 01"],"fullName":"Exercício 01 Ex01 - Válida - Questão 6","status":"passed","title":"Ex01 - Válida - Questão 6","duration":0.20873800000001097,"failureMessages":[],"meta":{}},{"ancestorTitles":["Exercício 01"],"fullName":"Exercício 01 Ex01 - Correta - Questão 6","status":"passed","title":"Ex01 - Correta - Questão 6","duration":0.1446849999999813,"failureMessages":[],"meta":{}},{"ancestorTitles":["Exercício 01"],"fullName":"Exercício 01 Ex01 - Válida - Questão 7","status":"passed","title":"Ex01 - Válida - Questão 7","duration":0.11957700000002092,"failureMessages":[],"meta":{}},{"ancestorTitles":["Exercício 01"],"fullName":"Exercício 01 Ex01 - Correta - Questão 7","status":"passed","title":"Ex01 - Correta - Questão 7","duration":0.19089099999999348,"failureMessages":[],"meta":{}},{"ancestorTitles":["Exercício 01"],"fullName":"Exercício 01 Ex01 - Válida - Questão 8","status":"passed","title":"Ex01 - Válida - Questão 8","duration":0.11829299999999421,"failureMessages":[],"meta":{}},{"ancestorTitles":["Exercício 01"],"fullName":"Exercício 01 Ex01 - Correta - Questão 8","status":"passed","title":"Ex01 - Correta - Questão 8","duration":0.11710600000000682,"failureMessages":[],"meta":{}},{"ancestorTitles":["Exercício 01"],"fullName":"Exercício 01 Ex01 - Válida - Questão 9","status":"passed","title":"Ex01 - Válida - Questão 9","duration":0.11544299999999907,"failureMessages":[],"meta":{}},{"ancestorTitles":["Exercício 01"],"fullName":"Exercício 01 Ex01 - Correta - Questão 9","status":"passed","title":"Ex01 - Correta - Questão 9","duration":0.09940000000000282,"failureMessages":[],"meta":{}},{"ancestorTitles":["Exercício 01"],"fullName":"Exercício 01 Ex01 - Válida - Questão 10","status":"passed","title":"Ex01 - Válida - Questão 10","duration":0.12066000000001509,"failureMessages":[],"meta":{}},{"ancestorTitles":["Exercício 01"],"fullName":"Exercício 01 Ex01 - Correta - Questão 10","status":"passed","title":"Ex01 - Correta - Questão 10","duration":0.10450700000001234,"failureMessages":[],"meta":{}}],"startTime":1778164307247,"endTime":1778164307254.1206,"status":"passed","message":"","name":"/home/vmca/Code/school/atv_pub/3d-05-lacos/ex01.test.js"},{"assertionResults":[{"ancestorTitles":["Exercício 02"],"fullName":"Exercício 02 Ex02 - Válida - Questão 1","status":"passed","title":"Ex02 - Válida - Questão 1","duration":2.0063189999999906,"failureMessages":[],"meta":{}},{"ancestorTitles":["Exercício 02"],"fullName":"Exercício 02 Ex02 - Correta - Questão 1","status":"passed","title":"Ex02 - Correta - Questão 1","duration":1.1474760000000117,"failureMessages":[],"meta":{}},{"ancestorTitles":["Exercício 02"],"fullName":"Exercício 02 Ex02 - Válida - Questão 2","status":"passed","title":"Ex02 - Válida - Questão 2","duration":0.24287200000000553,"failureMessages":[],"meta":{}},{"ancestorTitles":["Exercício 02"],"fullName":"Exercício 02 Ex02 - Correta - Questão 2","status":"passed","title":"Ex02 - Correta - Questão 2","duration":0.42357699999999454,"failureMessages":[],"meta":{}},{"ancestorTitles":["Exercício 02"],"fullName":"Exercício 02 Ex02 - Válida - Questão 3","status":"passed","title":"Ex02 - Válida - Questão 3","duration":0.2284320000000264,"failureMessages":[],"meta":{}},{"ancestorTitles":["Exercício 02"],"fullName":"Exercício 02 Ex02 - Correta - Questão 3","status":"passed","title":"Ex02 - Correta - Questão 3","duration":0.14027699999999754,"failureMessages":[],"meta":{}},{"ancestorTitles":["Exercício 02"],"fullName":"Exercício 02 Ex02 - Válida - Questão 4","status":"passed","title":"Ex02 - Válida - Questão 4","duration":0.22561099999998646,"failureMessages":[],"meta":{}},{"ancestorTitles":["Exercício 02"],"fullName":"Exercício 02 Ex02 - Correta - Questão 4","status":"failed","title":"Ex02 - Correta - Questão 4","duration":7.841094999999996,"failureMessages":["AssertionError: expected 100.5 to deeply equal 99\n    at /home/vmca/Code/school/atv_pub/3d-05-lacos/ex02.test.js:45:30\n    at file:///home/vmca/Code/school/atv_pub/3d-05-lacos/node_modules/@vitest/runner/dist/index.js:145:11\n    at file:///home/vmca/Code/school/atv_pub/3d-05-lacos/node_modules/@vitest/runner/dist/index.js:915:26\n    at file:///home/vmca/Code/school/atv_pub/3d-05-lacos/node_modules/@vitest/runner/dist/index.js:1243:20\n    at new Promise (<anonymous>)\n    at runWithTimeout (file:///home/vmca/Code/school/atv_pub/3d-05-lacos/node_modules/@vitest/runner/dist/index.js:1209:10)\n    at file:///home/vmca/Code/school/atv_pub/3d-05-lacos/node_modules/@vitest/runner/dist/index.js:1653:37\n    at Traces.$ (file:///home/vmca/Code/school/atv_pub/3d-05-lacos/node_modules/vitest/dist/chunks/traces.CCmnQaNT.js:142:27)\n    at trace (file:///home/vmca/Code/school/atv_pub/3d-05-lacos/node_modules/vitest/dist/chunks/test.B8ej_ZHS.js:239:21)\n    at runTest (file:///home/vmca/Code/school/atv_pub/3d-05-lacos/node_modules/@vitest/runner/dist/index.js:1653:12)"],"meta":{}},{"ancestorTitles":["Exercício 02"],"fullName":"Exercício 02 Ex02 - Válida - Questão 5","status":"passed","title":"Ex02 - Válida - Questão 5","duration":0.5011110000000087,"failureMessages":[],"meta":{}},{"ancestorTitles":["Exercício 02"],"fullName":"Exercício 02 Ex02 - Correta - Questão 5","status":"passed","title":"Ex02 - Correta - Questão 5","duration":0.5020629999999926,"failureMessages":[],"meta":{}},{"ancestorTitles":["Exercício 02"],"fullName":"Exercício 02 Ex02 - Válida - Questão 6","status":"passed","title":"Ex02 - Válida - Questão 6","duration":0.18012699999999882,"failureMessages":[],"meta":{}},{"ancestorTitles":["Exercício 02"],"fullName":"Exercício 02 Ex02 - Correta - Questão 6","status":"passed","title":"Ex02 - Correta - Questão 6","duration":0.15821299999998928,"failureMessages":[],"meta":{}},{"ancestorTitles":["Exercício 02"],"fullName":"Exercício 02 Ex02 - Válida - Questão 7","status":"passed","title":"Ex02 - Válida - Questão 7","duration":0.12600599999998963,"failureMessages":[],"meta":{}},{"ancestorTitles":["Exercício 02"],"fullName":"Exercício 02 Ex02 - Correta - Questão 7","status":"passed","title":"Ex02 - Correta - Questão 7","duration":0.24442700000000173,"failureMessages":[],"meta":{}},{"ancestorTitles":["Exercício 02"],"fullName":"Exercício 02 Ex02 - Válida - Questão 8","status":"passed","title":"Ex02 - Válida - Questão 8","duration":0.125222999999977,"failureMessages":[],"meta":{}},{"ancestorTitles":["Exercício 02"],"fullName":"Exercício 02 Ex02 - Correta - Questão 8","status":"passed","title":"Ex02 - Correta - Questão 8","duration":0.12823199999999702,"failureMessages":[],"meta":{}},{"ancestorTitles":["Exercício 02"],"fullName":"Exercício 02 Ex02 - Válida - Questão 9","status":"passed","title":"Ex02 - Válida - Questão 9","duration":0.11926300000001788,"failureMessages":[],"meta":{}},{"ancestorTitles":["Exercício 02"],"fullName":"Exercício 02 Ex02 - Correta - Questão 9","status":"passed","title":"Ex02 - Correta - Questão 9","duration":0.10972900000001573,"failureMessages":[],"meta":{}},{"ancestorTitles":["Exercício 02"],"fullName":"Exercício 02 Ex02 - Válida - Questão 10","status":"passed","title":"Ex02 - Válida - Questão 10","duration":0.12679799999997954,"failureMessages":[],"meta":{}},{"ancestorTitles":["Exercício 02"],"fullName":"Exercício 02 Ex02 - Correta - Questão 10","status":"passed","title":"Ex02 - Correta - Questão 10","duration":0.10466400000001386,"failureMessages":[],"meta":{}},{"ancestorTitles":["Exercício 02"],"fullName":"Exercício 02 Ex02 - Válida - Questão 11","status":"passed","title":"Ex02 - Válida - Questão 11","duration":0.114483000000007,"failureMessages":[],"meta":{}},{"ancestorTitles":["Exercício 02"],"fullName":"Exercício 02 Ex02 - Correta - Questão 11","status":"failed","title":"Ex02 - Correta - Questão 11","duration":1.9211260000000152,"failureMessages":["AssertionError: expected 4 to deeply equal [ 'tarântula', 'escorpião', …(2) ]\n    at /home/vmca/Code/school/atv_pub/3d-05-lacos/ex02.test.js:45:30\n    at file:///home/vmca/Code/school/atv_pub/3d-05-lacos/node_modules/@vitest/runner/dist/index.js:145:11\n    at file:///home/vmca/Code/school/atv_pub/3d-05-lacos/node_modules/@vitest/runner/dist/index.js:915:26\n    at file:///home/vmca/Code/school/atv_pub/3d-05-lacos/node_modules/@vitest/runner/dist/index.js:1243:20\n    at new Promise (<anonymous>)\n    at runWithTimeout (file:///home/vmca/Code/school/atv_pub/3d-05-lacos/node_modules/@vitest/runner/dist/index.js:1209:10)\n    at file:///home/vmca/Code/school/atv_pub/3d-05-lacos/node_modules/@vitest/runner/dist/index.js:1653:37\n    at Traces.$ (file:///home/vmca/Code/school/atv_pub/3d-05-lacos/node_modules/vitest/dist/chunks/traces.CCmnQaNT.js:142:27)\n    at trace (file:///home/vmca/Code/school/atv_pub/3d-05-lacos/node_modules/vitest/dist/chunks/test.B8ej_ZHS.js:239:21)\n    at runTest (file:///home/vmca/Code/school/atv_pub/3d-05-lacos/node_modules/@vitest/runner/dist/index.js:1653:12)"],"meta":{}},{"ancestorTitles":["Exercício 02"],"fullName":"Exercício 02 Ex02 - Válida - Questão 12","status":"passed","title":"Ex02 - Válida - Questão 12","duration":0.1422979999999825,"failureMessages":[],"meta":{}},{"ancestorTitles":["Exercício 02"],"fullName":"Exercício 02 Ex02 - Correta - Questão 12","status":"passed","title":"Ex02 - Correta - Questão 12","duration":0.10903200000001334,"failureMessages":[],"meta":{}}],"startTime":1778164307246,"endTime":1778164307264.1423,"status":"failed","message":"","name":"/home/vmca/Code/school/atv_pub/3d-05-lacos/ex02.test.js"}]}