{"numTotalTestSuites":3,"numPassedTestSuites":0,"numFailedTestSuites":3,"numPendingTestSuites":0,"numTotalTests":24,"numPassedTests":22,"numFailedTests":2,"numPendingTests":0,"numTodoTests":0,"snapshot":{"added":0,"failure":false,"filesAdded":0,"filesRemoved":0,"filesRemovedList":[],"filesUnmatched":0,"filesUpdated":0,"matched":0,"total":0,"unchecked":0,"uncheckedKeysByFile":[],"unmatched":0,"updated":0,"didUpdate":false},"startTime":1775259232781,"success":false,"testResults":[{"assertionResults":[],"startTime":1775259232781,"endTime":1775259232781,"status":"failed","message":"Failed to parse source for import analysis because the content contains invalid JS syntax. If you are using JSX, make sure to name the file with the .jsx or .tsx extension.","name":"/home/vicmca/CodeProjects/School/materiais/atv_pub/3d-05-lacos/ex01.test.js"},{"assertionResults":[{"ancestorTitles":["Exercício 02"],"fullName":"Exercício 02 Ex02 - Válida - Questão 1","status":"passed","title":"Ex02 - Válida - Questão 1","duration":2.7399489999999673,"failureMessages":[],"meta":{}},{"ancestorTitles":["Exercício 02"],"fullName":"Exercício 02 Ex02 - Correta - Questão 1","status":"passed","title":"Ex02 - Correta - Questão 1","duration":1.3589980000000423,"failureMessages":[],"meta":{}},{"ancestorTitles":["Exercício 02"],"fullName":"Exercício 02 Ex02 - Válida - Questão 2","status":"passed","title":"Ex02 - Válida - Questão 2","duration":0.5048419999999965,"failureMessages":[],"meta":{}},{"ancestorTitles":["Exercício 02"],"fullName":"Exercício 02 Ex02 - Correta - Questão 2","status":"passed","title":"Ex02 - Correta - Questão 2","duration":0.7636129999999639,"failureMessages":[],"meta":{}},{"ancestorTitles":["Exercício 02"],"fullName":"Exercício 02 Ex02 - Válida - Questão 3","status":"passed","title":"Ex02 - Válida - Questão 3","duration":0.4503050000000144,"failureMessages":[],"meta":{}},{"ancestorTitles":["Exercício 02"],"fullName":"Exercício 02 Ex02 - Correta - Questão 3","status":"passed","title":"Ex02 - Correta - Questão 3","duration":0.40259200000002693,"failureMessages":[],"meta":{}},{"ancestorTitles":["Exercício 02"],"fullName":"Exercício 02 Ex02 - Válida - Questão 4","status":"passed","title":"Ex02 - Válida - Questão 4","duration":0.6541709999999625,"failureMessages":[],"meta":{}},{"ancestorTitles":["Exercício 02"],"fullName":"Exercício 02 Ex02 - Correta - Questão 4","status":"failed","title":"Ex02 - Correta - Questão 4","duration":15.750552000000027,"failureMessages":["AssertionError: expected 100.5 to deeply equal 99\n    at /home/vicmca/CodeProjects/School/materiais/atv_pub/3d-05-lacos/ex02.test.js:45:30\n    at file:///home/vicmca/CodeProjects/School/materiais/atv_pub/3d-05-lacos/node_modules/@vitest/runner/dist/index.js:145:11\n    at file:///home/vicmca/CodeProjects/School/materiais/atv_pub/3d-05-lacos/node_modules/@vitest/runner/dist/index.js:915:26\n    at file:///home/vicmca/CodeProjects/School/materiais/atv_pub/3d-05-lacos/node_modules/@vitest/runner/dist/index.js:1243:20\n    at new Promise (<anonymous>)\n    at runWithTimeout (file:///home/vicmca/CodeProjects/School/materiais/atv_pub/3d-05-lacos/node_modules/@vitest/runner/dist/index.js:1209:10)\n    at file:///home/vicmca/CodeProjects/School/materiais/atv_pub/3d-05-lacos/node_modules/@vitest/runner/dist/index.js:1653:37\n    at Traces.$ (file:///home/vicmca/CodeProjects/School/materiais/atv_pub/3d-05-lacos/node_modules/vitest/dist/chunks/traces.CCmnQaNT.js:142:27)\n    at trace (file:///home/vicmca/CodeProjects/School/materiais/atv_pub/3d-05-lacos/node_modules/vitest/dist/chunks/test.B8ej_ZHS.js:239:21)\n    at runTest (file:///home/vicmca/CodeProjects/School/materiais/atv_pub/3d-05-lacos/node_modules/@vitest/runner/dist/index.js:1653:12)"],"meta":{}},{"ancestorTitles":["Exercício 02"],"fullName":"Exercício 02 Ex02 - Válida - Questão 5","status":"passed","title":"Ex02 - Válida - Questão 5","duration":1.0804650000000038,"failureMessages":[],"meta":{}},{"ancestorTitles":["Exercício 02"],"fullName":"Exercício 02 Ex02 - Correta - Questão 5","status":"passed","title":"Ex02 - Correta - Questão 5","duration":0.8863660000000095,"failureMessages":[],"meta":{}},{"ancestorTitles":["Exercício 02"],"fullName":"Exercício 02 Ex02 - Válida - Questão 6","status":"passed","title":"Ex02 - Válida - Questão 6","duration":0.278616999999997,"failureMessages":[],"meta":{}},{"ancestorTitles":["Exercício 02"],"fullName":"Exercício 02 Ex02 - Correta - Questão 6","status":"passed","title":"Ex02 - Correta - Questão 6","duration":0.24362600000000612,"failureMessages":[],"meta":{}},{"ancestorTitles":["Exercício 02"],"fullName":"Exercício 02 Ex02 - Válida - Questão 7","status":"passed","title":"Ex02 - Válida - Questão 7","duration":0.20593000000002348,"failureMessages":[],"meta":{}},{"ancestorTitles":["Exercício 02"],"fullName":"Exercício 02 Ex02 - Correta - Questão 7","status":"passed","title":"Ex02 - Correta - Questão 7","duration":0.36923699999999826,"failureMessages":[],"meta":{}},{"ancestorTitles":["Exercício 02"],"fullName":"Exercício 02 Ex02 - Válida - Questão 8","status":"passed","title":"Ex02 - Válida - Questão 8","duration":0.19414299999999685,"failureMessages":[],"meta":{}},{"ancestorTitles":["Exercício 02"],"fullName":"Exercício 02 Ex02 - Correta - Questão 8","status":"passed","title":"Ex02 - Correta - Questão 8","duration":0.20775000000003274,"failureMessages":[],"meta":{}},{"ancestorTitles":["Exercício 02"],"fullName":"Exercício 02 Ex02 - Válida - Questão 9","status":"passed","title":"Ex02 - Válida - Questão 9","duration":0.18883900000002996,"failureMessages":[],"meta":{}},{"ancestorTitles":["Exercício 02"],"fullName":"Exercício 02 Ex02 - Correta - Questão 9","status":"passed","title":"Ex02 - Correta - Questão 9","duration":0.1731760000000122,"failureMessages":[],"meta":{}},{"ancestorTitles":["Exercício 02"],"fullName":"Exercício 02 Ex02 - Válida - Questão 10","status":"passed","title":"Ex02 - Válida - Questão 10","duration":0.3798110000000179,"failureMessages":[],"meta":{}},{"ancestorTitles":["Exercício 02"],"fullName":"Exercício 02 Ex02 - Correta - Questão 10","status":"passed","title":"Ex02 - Correta - Questão 10","duration":0.18565300000000207,"failureMessages":[],"meta":{}},{"ancestorTitles":["Exercício 02"],"fullName":"Exercício 02 Ex02 - Válida - Questão 11","status":"passed","title":"Ex02 - Válida - Questão 11","duration":0.18778099999997266,"failureMessages":[],"meta":{}},{"ancestorTitles":["Exercício 02"],"fullName":"Exercício 02 Ex02 - Correta - Questão 11","status":"failed","title":"Ex02 - Correta - Questão 11","duration":3.3561689999999658,"failureMessages":["AssertionError: expected 4 to deeply equal [ 'tarântula', 'escorpião', …(2) ]\n    at /home/vicmca/CodeProjects/School/materiais/atv_pub/3d-05-lacos/ex02.test.js:45:30\n    at file:///home/vicmca/CodeProjects/School/materiais/atv_pub/3d-05-lacos/node_modules/@vitest/runner/dist/index.js:145:11\n    at file:///home/vicmca/CodeProjects/School/materiais/atv_pub/3d-05-lacos/node_modules/@vitest/runner/dist/index.js:915:26\n    at file:///home/vicmca/CodeProjects/School/materiais/atv_pub/3d-05-lacos/node_modules/@vitest/runner/dist/index.js:1243:20\n    at new Promise (<anonymous>)\n    at runWithTimeout (file:///home/vicmca/CodeProjects/School/materiais/atv_pub/3d-05-lacos/node_modules/@vitest/runner/dist/index.js:1209:10)\n    at file:///home/vicmca/CodeProjects/School/materiais/atv_pub/3d-05-lacos/node_modules/@vitest/runner/dist/index.js:1653:37\n    at Traces.$ (file:///home/vicmca/CodeProjects/School/materiais/atv_pub/3d-05-lacos/node_modules/vitest/dist/chunks/traces.CCmnQaNT.js:142:27)\n    at trace (file:///home/vicmca/CodeProjects/School/materiais/atv_pub/3d-05-lacos/node_modules/vitest/dist/chunks/test.B8ej_ZHS.js:239:21)\n    at runTest (file:///home/vicmca/CodeProjects/School/materiais/atv_pub/3d-05-lacos/node_modules/@vitest/runner/dist/index.js:1653:12)"],"meta":{}},{"ancestorTitles":["Exercício 02"],"fullName":"Exercício 02 Ex02 - Válida - Questão 12","status":"passed","title":"Ex02 - Válida - Questão 12","duration":0.28480100000001585,"failureMessages":[],"meta":{}},{"ancestorTitles":["Exercício 02"],"fullName":"Exercício 02 Ex02 - Correta - Questão 12","status":"passed","title":"Ex02 - Correta - Questão 12","duration":0.19464099999999007,"failureMessages":[],"meta":{}}],"startTime":1775259233147,"endTime":1775259233179.1946,"status":"failed","message":"","name":"/home/vicmca/CodeProjects/School/materiais/atv_pub/3d-05-lacos/ex02.test.js"}]}